bin/__init__.py
bin/amplicon.py
bin/smel.py
src/__init__.py
src/data_import.py
src/denoising.py
src/diversity.py
src/phylogeny.py
src/remove_adapters.py
src/taxonomy_classification.py
src/utils.py
smel-0.0.3.dist-info/METADATA
smel-0.0.3.dist-info/WHEEL
smel-0.0.3.dist-info/entry_points.txt
smel-0.0.3.dist-info/top_level.txt
smel-0.0.3.dist-info/RECORD
