Metadata-Version: 2.1
Name: smel
Version: 0.0.3
Summary: Automatic analysis pipeline
Home-page: https://github.com/KyuKyu-dplearn/smel
Author: Kyu-Chan Lee
Author-email: lkcmsd@gmail.com
Classifier: Programming Language :: Python :: 3
Classifier: License :: OSI Approved :: MIT License
Requires-Dist: biopython ==1.81
Requires-Dist: conorm ==1.2.0
Requires-Dist: pyfiglet ==0.8.post1
Requires-Dist: termcolor ==2.3.0
Requires-Dist: wget ==3.2.0
